tubesml/CV_score.py
tubesml/__init__.py
tubesml/base.py
tubesml/clean.py
tubesml/dummy.py
tubesml/encoders.py
tubesml/error_analysis.py
tubesml/explore.py
tubesml/model_comparison.py
tubesml/model_inspection.py
tubesml/model_selection.py
tubesml/pca.py
tubesml/poly.py
tubesml/report.py
tubesml/scale.py
tubesml/shap_values.py
tubesml/stacker.py
tubesml/utility.py
tubesml/visualize_error.py
tubesml-1.0.2.dist-info/licenses/LICENSE
tubesml-1.0.2.dist-info/METADATA
tubesml-1.0.2.dist-info/WHEEL
tubesml-1.0.2.dist-info/top_level.txt
tubesml-1.0.2.dist-info/RECORD
