Metadata-Version: 2.4
Name: tubesml
Version: 1.0.2
Summary: tubesML, a package that allows for flexible ML pipelines, model validation, and model inspection
Home-page: https://pypi.org/project/tubesml/
Download-URL: https://github.com/lucabasa/tubesML
Author: Luca Basanisi
Author-email: Luca Basanisi <luca.basanisi@gmail.com>
Maintainer: Luca Basanisi
Maintainer-email: Luca Basanisi <luca.basanisi@gmail.com>
License:                                  Apache License
Project-URL: Source, https://github.com/lucabasa/tubesML
Project-URL: Documentation, https://tubesml.readthedocs.io/
Classifier: Development Status :: 4 - Beta
Classifier: Programming Language :: Python
Classifier: Programming Language :: Python :: 3.10
Classifier: Intended Audience :: Science/Research
Classifier: Intended Audience :: Developers
Classifier: Operating System :: Microsoft :: Windows
Classifier: Operating System :: POSIX
Classifier: Operating System :: Unix
Classifier: Operating System :: MacOS
Requires-Python: >=3.7
License-File: LICENSE
Requires-Dist: kneed==0.8.5
Requires-Dist: matplotlib>=3.7.2
Requires-Dist: pandas>=2.2.2
Requires-Dist: scikit-learn<1.6.1,>=1.2.2
Requires-Dist: seaborn>=0.12.2
Requires-Dist: shap>=0.44.1
Provides-Extra: testing
Requires-Dist: pytest==8.2.2; extra == "testing"
Requires-Dist: coverage==7.5.3; extra == "testing"
Requires-Dist: xgboost==2.1.0; extra == "testing"
Requires-Dist: lightgbm==4.4.0; extra == "testing"
Dynamic: author
Dynamic: download-url
Dynamic: home-page
Dynamic: license-file
Dynamic: maintainer
Dynamic: requires-python
